cachely/__init__.py
cachely/cache.py
pycachely_rj-1.0.0.dist-info/METADATA
pycachely_rj-1.0.0.dist-info/WHEEL
pycachely_rj-1.0.0.dist-info/RECORD
