Metadata-Version: 2.4
Name: pycachely-rj
Version: 1.0.0
Summary: Simple in-memory caching with TTL support
Project-URL: Homepage, https://github.com/RedJohnx/pypi_warehouse
Project-URL: Repository, https://github.com/RedJohnx/pypi_warehouse/tree/main/packages/cachely
Author-email: RedJohnx <redjohnx@example.com>
License-Expression: MIT
Keywords: cache,caching,decorator,memoize,ttl
Classifier: Development Status :: 5 - Production/Stable
Classifier: Intended Audience :: Developers
Classifier: License :: OSI Approved :: MIT License
Classifier: Programming Language :: Python :: 3
Classifier: Programming Language :: Python :: 3.8
Classifier: Programming Language :: Python :: 3.9
Classifier: Programming Language :: Python :: 3.10
Classifier: Programming Language :: Python :: 3.11
Classifier: Programming Language :: Python :: 3.12
Requires-Python: >=3.8
